{
  "routes": [
    {
      "method": "GET",
      "path": "/shippings",
      "handler": "shippings.find",
      "config": {
        "policies": []
      }
    },
    {
      "method": "GET",
      "path": "/shippings/count",
      "handler": "shippings.count",
      "config": {
        "policies": []
      }
    },
    {
      "method": "GET",
      "path": "/shippings/:id",
      "handler": "shippings.findOne",
      "config": {
        "policies": []
      }
    },
    {
      "method": "POST",
      "path": "/shippings",
      "handler": "shippings.create",
      "config": {
        "policies": []
      }
    },
    {
      "method": "PUT",
      "path": "/shippings/:id",
      "handler": "shippings.update",
      "config": {
        "policies": []
      }
    },
    {
      "method": "DELETE",
      "path": "/shippings/:id",
      "handler": "shippings.delete",
      "config": {
        "policies": []
      }
    }
  ]
}
